EpyNN-1.2.13.data/scripts/epynn
epynn/__init__.py
epynn/initialize.py
epynn/settings.py
epynn/commons/__init__.py
epynn/commons/io.py
epynn/commons/library.py
epynn/commons/logs.py
epynn/commons/loss.py
epynn/commons/maths.py
epynn/commons/metrics.py
epynn/commons/models.py
epynn/commons/plot.py
epynn/commons/schedule.py
epynn/convolution/__init__.py
epynn/convolution/backward.py
epynn/convolution/forward.py
epynn/convolution/models.py
epynn/convolution/parameters.py
epynn/dense/__init__.py
epynn/dense/backward.py
epynn/dense/forward.py
epynn/dense/models.py
epynn/dense/parameters.py
epynn/dropout/__init__.py
epynn/dropout/backward.py
epynn/dropout/forward.py
epynn/dropout/models.py
epynn/dropout/parameters.py
epynn/embedding/__init__.py
epynn/embedding/backward.py
epynn/embedding/dataset.py
epynn/embedding/forward.py
epynn/embedding/models.py
epynn/embedding/parameters.py
epynn/flatten/__init__.py
epynn/flatten/backward.py
epynn/flatten/forward.py
epynn/flatten/models.py
epynn/flatten/parameters.py
epynn/gru/__init__.py
epynn/gru/backward.py
epynn/gru/forward.py
epynn/gru/models.py
epynn/gru/parameters.py
epynn/lstm/__init__.py
epynn/lstm/backward.py
epynn/lstm/forward.py
epynn/lstm/models.py
epynn/lstm/parameters.py
epynn/network/__init__.py
epynn/network/backward.py
epynn/network/evaluate.py
epynn/network/forward.py
epynn/network/hyperparameters.py
epynn/network/initialize.py
epynn/network/models.py
epynn/network/report.py
epynn/network/training.py
epynn/pooling/__init__.py
epynn/pooling/backward.py
epynn/pooling/forward.py
epynn/pooling/models.py
epynn/pooling/parameters.py
epynn/rnn/__init__.py
epynn/rnn/backward.py
epynn/rnn/forward.py
epynn/rnn/models.py
epynn/rnn/parameters.py
epynn/template/__init__.py
epynn/template/backward.py
epynn/template/forward.py
epynn/template/models.py
epynn/template/parameters.py
epynnlive/__init__.py
epynnlive/author_music/__init__.py
epynnlive/author_music/prepare_dataset.py
epynnlive/author_music/settings.py
EpyNN-1.2.13.dist-info/LICENSE
EpyNN-1.2.13.dist-info/METADATA
EpyNN-1.2.13.dist-info/WHEEL
EpyNN-1.2.13.dist-info/top_level.txt
EpyNN-1.2.13.dist-info/RECORD
