Metadata-Version: 2.1
Name: EpyNN
Version: 1.2.13
Summary: EpyNN: Educational python for Neural Networks.
Home-page: https://github.com/synthaze/epynn
Author: Florian Malard and Stéphanie Olivier-Van Stichelen
Author-email: florian.malard@gmail.com
License: GPL-3.0 License
Project-URL: Bug Tracker, https://github.com/synthaze/epynn/issues
Platform: UNKNOWN
Classifier: License :: OSI Approved :: GNU General Public License v3 or later (GPLv3+)
Classifier: Programming Language :: Python :: 3.7
Classifier: Operating System :: OS Independent
Requires-Python: >=3.7
Requires-Dist: Pillow (==8.3.1)
Requires-Dist: Pygments (==2.10.0)
Requires-Dist: cycler (==0.10.0)
Requires-Dist: jupyter (==1.0.0)
Requires-Dist: kiwisolver (==1.3.2)
Requires-Dist: matplotlib
Requires-Dist: nbconvert (==5.4.1)
Requires-Dist: numpy (==1.21.2)
Requires-Dist: pyparsing (==2.4.7)
Requires-Dist: python-dateutil (==2.8.2)
Requires-Dist: scipy (==1.6.3)
Requires-Dist: six (==1.16.0)
Requires-Dist: tabulate (==0.8.9)
Requires-Dist: termcolor (==1.1.0)
Requires-Dist: texttable (==1.6.4)
Requires-Dist: utilsovs-pkg
Requires-Dist: wget (==3.2)
